precious/__init__.py
precious/canine.py
precious/eva_attention.py
precious/models.py
precious/tfree.py
precious_nlp-0.1.2.dist-info/licenses/LICENSE
precious_nlp-0.1.2.dist-info/METADATA
precious_nlp-0.1.2.dist-info/WHEEL
precious_nlp-0.1.2.dist-info/top_level.txt
precious_nlp-0.1.2.dist-info/RECORD
