Metadata-Version: 2.4
Name: precious-nlp
Version: 0.1.2
Summary: A tokenizer-free NLP library with T-FREE, CANINE, and byte-level approaches
Home-page: https://github.com/bimri/precious
Author: bimri
Author-email: bimri <bimri@outlook.com>
Maintainer-email: bimri <bimri@outlook.com>
License: MIT
Project-URL: Homepage, https://github.com/bimri/precious
Project-URL: Repository, https://github.com/bimri/precious
Project-URL: Documentation, https://github.com/bimri/precious/blob/master/docs/API_REFERENCE.md
Project-URL: Bug Reports, https://github.com/bimri/precious/issues
Project-URL: Changelog, https://github.com/bimri/precious/blob/master/CHANGELOG.md
Keywords: tokenization,nlp,transformers,tokenizer-free,canine,tfree,byte-level,natural-language-processing,deep-learning,pytorch
Classifier: Development Status :: 4 - Beta
Classifier: Intended Audience :: Developers
Classifier: Intended Audience :: Science/Research
Classifier: License :: OSI Approved :: MIT License
Classifier: Operating System :: OS Independent
Classifier: Programming Language :: Python :: 3
Classifier: Programming Language :: Python :: 3.8
Classifier: Programming Language :: Python :: 3.9
Classifier: Programming Language :: Python :: 3.10
Classifier: Programming Language :: Python :: 3.11
Classifier: Programming Language :: Python :: 3.12
Classifier: Topic :: Scientific/Engineering :: Artificial Intelligence
Classifier: Topic :: Software Development :: Libraries :: Python Modules
Classifier: Topic :: Text Processing :: Linguistic
Requires-Python: >=3.8
License-File: LICENSE
Requires-Dist: torch>=1.9.0
Requires-Dist: numpy>=1.19.0
Provides-Extra: dev
Requires-Dist: pytest>=6.0; extra == "dev"
Requires-Dist: pytest-cov>=2.0; extra == "dev"
Requires-Dist: black>=22.0; extra == "dev"
Requires-Dist: isort>=5.0; extra == "dev"
Requires-Dist: flake8>=4.0; extra == "dev"
Provides-Extra: benchmarks
Requires-Dist: psutil>=5.8.0; extra == "benchmarks"
Provides-Extra: docs
Requires-Dist: sphinx>=4.0; extra == "docs"
Requires-Dist: sphinx-rtd-theme>=1.0; extra == "docs"
Provides-Extra: all
Requires-Dist: pytest>=6.0; extra == "all"
Requires-Dist: pytest-cov>=2.0; extra == "all"
Requires-Dist: black>=22.0; extra == "all"
Requires-Dist: isort>=5.0; extra == "all"
Requires-Dist: flake8>=4.0; extra == "all"
Requires-Dist: psutil>=5.8.0; extra == "all"
Requires-Dist: sphinx>=4.0; extra == "all"
Requires-Dist: sphinx-rtd-theme>=1.0; extra == "all"
Dynamic: author
Dynamic: home-page
Dynamic: license-file
Dynamic: requires-python
